{
  "meta": {
    "title": "Shop – Sanddorn-Essenzen wählen | AmberNord",
    "description": "Entdecken Sie AmberNords Bio-Sanddorn-Essenzen: The Starter, The Habit und The Protocol. Reine nordische Lebenskraft, direkt aus Aarau in die Schweiz.",
    "canonical": "https://ambernord.ch/shop/",
    "slug": "/shop/",
    "robots": "index, follow",
    "og": {
      "title": "AmberNord Sanddorn-Essenzen – Wählen Sie Ihr Paket",
      "description": "The Starter, The Habit, The Protocol. Premium Bio-Sanddorn für Fokus, Energie und Longevity. Ab 24.90 CHF.",
      "image": "https://res.cloudinary.com/dt6ksxuqf/image/upload/f_auto,q_auto,w_1200/v1774798926/ambernord-sanddornsaft-kur-3er-pack-longevity-biohacking.webp_cg74qe",
      "type": "website"
    },
    "hreflang": {
      "de": "https://ambernord.ch/shop/",
      "en": "https://ambernord.ch/en/shop/",
      "fr": "https://ambernord.ch/fr/shop/",
      "it": "https://ambernord.ch/it/shop/",
      "x-default": "https://ambernord.ch/shop/"
    }
  },
  "header": {
    "eyebrow": "Sanddorn-Essenzen",
    "h1": "Wählen Sie Ihr <span>Elixier</span>"
  },
  "sections": [
    {
      "id": "shop-grid",
      "heading": "Produktauswahl"
    }
  ],
  "products": [
    {
      "id": "starter",
      "slug": "/the-starter/",
      "image": {
        "cloudinaryId": "v1774798945/ambernord-bio-sanddornsaft-zelt-edition-250ml-schweiz.webp_f3eaz0",
        "alt": "The Starter AmberNord Elixier – 250ml Flasche",
        "width": 400,
        "height": 400
      },
      "title": "The Starter",
      "quantity": "1x 250ml",
      "price": "24.90 CHF",
      "daily": "≈ 2.49 CHF / Tag",
      "subtitle": "Das zelluläre Erwachen.",
      "body": "Spüren Sie den Unterschied. Lösen Sie den mentalen Nebel auf und fluten Sie Ihren Körper mit reiner, nordischer Lebenskraft. Der kompromisslose erste Schritt zu mehr Fokus.",
      "scienceBox": {
        "heading": "Ihr Sofort-Effekt",
        "items": [
          "Spürbare Klarheit ab dem 1. Schluck.",
          "Eine der seltenen Quellen aller 4 Omega-Fettsäuren.",
          "10 Tage reine, zelluläre Energie."
        ]
      },
      "buttons": {
        "primary": {
          "label": "1x Elixier Bestellen",
          "href": "https://buy.stripe.com/6oU8wR3PBagV3GpaPBbQY00"
        },
        "subscription": null
      },
      "shipping": {
        "highlight": "Logistik:",
        "text": " Direktversand aus Aarau, CH."
      }
    },
    {
      "id": "habit",
      "slug": "/the-habit/",
      "image": {
        "cloudinaryId": "v1774798926/ambernord-sanddornsaft-kur-3er-pack-longevity-biohacking.webp_cg74qe",
        "alt": "The Habit AmberNord Elixier – 3er Pack Kur",
        "width": 400,
        "height": 400
      },
      "badge": {
        "type": "bestseller",
        "label": "AM BELIEBTESTEN"
      },
      "title": "The Habit",
      "quantity": "3x 250ml",
      "price": "69.00 CHF",
      "savings": "−8 % vs. Starter",
      "daily": "≈ 2.30 CHF / Tag",
      "subtitle": "Das Ende künstlicher Energie.",
      "body": "Verabschieden Sie sich von toxischen Energie-Löchern durch künstliche Energy-Drinks und synthetisches Taurin. Verankern Sie anhaltenden Fokus in Ihrer Routine.",
      "scienceBox": {
        "heading": "Die Transformation",
        "items": [
          "Messbarer Fokus ohne Nachmittags-Tief.",
          "Flutet die Zellen mit seltenem Omega-7.",
          "Schützt und regeneriert die Schleimhäute.",
          "30 Tage kompromisslose Performance."
        ]
      },
      "buttons": {
        "primary": {
          "label": "3x Elixier Bestellen",
          "href": "https://buy.stripe.com/cNi3cx3PB2Ot6SB4rdbQY01"
        },
        "subscription": {
          "discountLabel": "Mit Abo Sparen (-7.7%)",
          "price": "63.00 CHF",
          "subtext": "Pro Monat",
          "guarantee": "✓ Jederzeit kündbar",
          "href": "https://buy.stripe.com/aFa6oJ71N60F4Kt3n9bQY04"
        }
      },
      "shipping": {
        "highlight": "Gratis Premium-Versand",
        "text": " CH."
      }
    },
    {
      "id": "protocol",
      "slug": "/the-protocol/",
      "image": {
        "cloudinaryId": "v1774798936/ambernord-sanddorn-elixier-6er-vorratspack-premium-qualit%C3%A4t.webp_v9c6bd",
        "alt": "The Protocol AmberNord Elixier – 6er Vorratspack",
        "width": 400,
        "height": 400
      },
      "badge": null,
      "title": "The Protocol",
      "quantity": "6x 250ml",
      "price": "129.00 CHF",
      "savings": "−14 % vs. Starter",
      "daily": "≈ 2.15 CHF / Tag",
      "subtitle": "Das ultimative Biohacking-Tool.",
      "body": "Entworfen für High-Performer. Maximieren Sie Ihre Longevity und bauen Sie einen unzerstörbaren immunologischen Schild auf.",
      "scienceBox": {
        "heading": "Das Meister-Level",
        "items": [
          "Lückenloser Zellschutz für Monate.",
          "Der natürliche Schild gegen Blaulicht.",
          "Über 190 bioaktive Wirkstoffe aktiv.",
          "Maximale Ausbeute, bester Preis."
        ]
      },
      "buttons": {
        "primary": {
          "label": "6x Elixier Bestellen",
          "href": "https://buy.stripe.com/3cI6oJbi3gFjb8R8HtbQY02"
        },
        "subscription": {
          "discountLabel": "Mit Abo Sparen (-9%)",
          "price": "119.00 CHF",
          "subtext": "Pro Monat",
          "guarantee": "✓ Jederzeit kündbar",
          "href": "https://buy.stripe.com/9B600lcm7bkZ0ud2j5bQY05"
        }
      },
      "shipping": {
        "highlight": "Gratis Premium-Versand",
        "text": " CH."
      }
    }
  ]
}